Add_library/__init__.py
Add_library/add.py
Add_library-1.0.dist-info/METADATA
Add_library-1.0.dist-info/WHEEL
Add_library-1.0.dist-info/top_level.txt
Add_library-1.0.dist-info/RECORD
