Metadata-Version: 2.1
Name: Add_library
Version: 1.0
Summary: This is the simplest module for add two numbers
Home-page: https://github.com/FessLeru/
Author: Dr_Andreiika
Author-email: sedunovandrey2007@gmail.com
Project-URL: GitHub, https://github.com/FessLeru/
Keywords: Add
Classifier: Programming Language :: Python :: 3.11
Classifier: License :: OSI Approved :: MIT License
Classifier: Operating System :: OS Independent
Requires-Python: >=3.6
